[
    {
        "id": 1,
        "question": "പ്രകാശത്തെക്കുറിച്ചുള്ള പഠനം ഭൗതികശാസ്ത്രത്തിൻ്റെ ഏത് ശാഖയിലാണ് വരുന്നത്?",
        "options": [
            "താപഗതികം",
            "ബലതന്ത്രം",
            "പ്രകാശശാസ്ത്രം",
            "ശബ്ദശാസ്ത്രം"
        ],
        "answer": "പ്രകാശശാസ്ത്രം"
    },
    {
        "id": 2,
        "question": "ഒരു വസ്തുവിൽ അടങ്ങിയിരിക്കുന്ന ദ്രവ്യത്തിൻ്റെ അളവിനെ സൂചിപ്പിക്കുന്ന ഭൗതിക അളവ് ഏതാണ്?",
        "options": [
            "വ്യാപ്തം",
            "സാന്ദ്രത",
            "പിണ്ഡം",
            "ഭാരം"
        ],
        "answer": "പിണ്ഡം"
    },
    {
        "id": 3,
        "question": "അന്താരാഷ്ട്ര ഏകക സമ്പ്രദായത്തിൽ (SI) സമയത്തിൻ്റെ യൂണിറ്റ് എന്താണ്?",
        "options": [
            "മിനിറ്റ്",
            "മണിക്കൂർ",
            "സെക്കൻഡ്",
            "ദിവസം"
        ],
        "answer": "സെക്കൻഡ്"
    },
    {
        "id": 4,
        "question": "താഴെക്കൊടുത്തിരിക്കുന്നവയിൽ അടിസ്ഥാന ഭൗതിക അളവ് ഏതാണ്?",
        "options": [
            "വേഗത",
            "ബലം",
            "നീളം",
            "പ്രവേഗം"
        ],
        "answer": "നീളം"
    },
    {
        "id": 5,
        "question": "വൈദ്യുതിയെയും കാന്തികതയെയും കുറിച്ചുള്ള പഠനം ഭൗതികശാസ്ത്രത്തിൻ്റെ ഏത് ശാഖയിലാണ് ഉൾപ്പെടുന്നത്?",
        "options": [
            "അണുഭൗതികം",
            "ഖരസ്ഥിതി ഭൗതികം",
            "വൈദ്യുതകാന്തികത",
            "ജ്യോതിർഭൗതികം"
        ],
        "answer": "വൈദ്യുതകാന്തികത"
    },
    {
        "id": 6,
        "question": "ദ്രവ്യത്തിൻ്റെ നാലാമത്തെ അവസ്ഥ ഏതാണ്?",
        "options": [
            "ഖരം",
            "ദ്രാവകം",
            "വാതകം",
            "പ്ലാസ്മ"
        ],
        "answer": "പ്ലാസ്മ"
    },
    {
        "id": 7,
        "question": "SI സമ്പ്രദായത്തിൽ താപനിലയുടെ അടിസ്ഥാന യൂണിറ്റ് ഏതാണ്?",
        "options": [
            "സെൽഷ്യസ്",
            "ഫാരൻഹീറ്റ്",
            "കെൽവിൻ",
            "റാങ്കൈൻ"
        ],
        "answer": "കെൽവിൻ"
    },
    {
        "id": 8,
        "question": "ഒരു നിശ്ചിത സമയത്തിൽ സഞ്ചരിക്കുന്ന ദൂരത്തെ എന്ത് വിളിക്കുന്നു?",
        "options": [
            "പ്രവേഗം",
            "ത്വരണം",
            "വേഗത",
            "സ്ഥാനാന്തരം"
        ],
        "answer": "വേഗത"
    },
    {
        "id": 9,
        "question": "ശബ്ദത്തെക്കുറിച്ചുള്ള പഠനം ഭൗതികശാസ്ത്രത്തിൻ്റെ ഏത് ശാഖയിലാണ് വരുന്നത്?",
        "options": [
            "പ്രകാശശാസ്ത്രം",
            "താപഗതികം",
            "അക്കോസ്റ്റിക്സ്",
            "ബലതന്ത്രം"
        ],
        "answer": "അക്കോസ്റ്റിക്സ്"
    },
    {
        "id": 10,
        "question": "തന്മാത്രകൾ വളരെ അടുത്ത് പായ്ക്ക് ചെയ്യപ്പെട്ടിരിക്കുന്ന ദ്രവ്യത്തിൻ്റെ അവസ്ഥ ഏതാണ്?",
        "options": [
            "വാതകം",
            "ദ്രാവകം",
            "ഖരം",
            "പ്ലാസ്മ"
        ],
        "answer": "ഖരം"
    },
    {
        "id": 11,
        "question": "SI സമ്പ്രദായത്തിൽ ഊർജ്ജത്തിൻ്റെ യൂണിറ്റ് എന്താണ്?",
        "options": [
            "വാട്ട്",
            "ജൂൾ",
            "ന്യൂട്ടൺ",
            "പാസ്കൽ"
        ],
        "answer": "ജൂൾ"
    },
    {
        "id": 12,
        "question": "ഒരു വെക്റ്റർ അളവിന് ഉദാഹരണം ഏതാണ്?",
        "options": [
            "സമയം",
            "പിണ്ഡം",
            "പ്രവേഗം",
            "ദൂരം"
        ],
        "answer": "പ്രവേഗം"
    },
    {
        "id": 13,
        "question": "അണുക്കളെയും അവയുടെ ഘടകങ്ങളെയും കുറിച്ചുള്ള പഠനം ഭൗതികശാസ്ത്രത്തിൻ്റെ ഏത് ശാഖയിലാണ്?",
        "options": [
            "ഖരസ്ഥിതി ഭൗതികം",
            "അന്തരീക്ഷ ഭൗതികം",
            "അണുഭൗതികം",
            "തന്മാത്രാ ഭൗതികം"
        ],
        "answer": "അണുഭൗതികം"
    },
    {
        "id": 14,
        "question": "ദ്രാവകങ്ങൾക്ക് ഒഴുകാൻ കഴിയുന്നതിനുള്ള കാരണം എന്താണ്?",
        "options": [
            "നിശ്ചിത ആകൃതി",
            "നിശ്ചിത വ്യാപ്തം",
            "തന്മാത്രകൾ തമ്മിലുള്ള അകലം",
            "ശക്തമായ ആകർഷണ ബലം"
        ],
        "answer": "തന്മാത്രകൾ തമ്മിലുള്ള അകലം"
    },
    {
        "id": 15,
        "question": "SI സമ്പ്രദായത്തിൽ ബലത്തിൻ്റെ യൂണിറ്റ് എന്താണ്?",
        "options": [
            "ജൂൾ",
            "വാട്ട്",
            "ന്യൂട്ടൺ",
            "പാസ്കൽ"
        ],
        "answer": "ന്യൂട്ടൺ"
    },
    {
        "id": 16,
        "question": "താഴെക്കൊടുത്തിരിക്കുന്നവയിൽ സ്കേലാർ അളവ് ഏതാണ്?",
        "options": [
            "ബലം",
            "പ്രവേഗം",
            "ത്വരണം",
            "ദൂരം"
        ],
        "answer": "ദൂരം"
    },
    {
        "id": 17,
        "question": "നക്ഷത്രങ്ങളെയും ഗ്രഹങ്ങളെയും കുറിച്ചുള്ള പഠനം ഭൗതികശാസ്ത്രത്തിൻ്റെ ഏത് ശാഖയിലാണ്?",
        "options": [
            "തെർമോഡൈനാമിക്സ്",
            "ജ്യോതിർഭൗതികം",
            "ഒപ്റ്റിക്സ്",
            "മെക്കാനിക്സ്"
        ],
        "answer": "ജ്യോതിർഭൗതികം"
    },
    {
        "id": 18,
        "question": "വാതക തന്മാത്രകളുടെ ചലനം എങ്ങനെയായിരിക്കും?",
        "options": [
            "ക്രമമായ ചലനം",
            "ചലനമില്ല",
            "ക്രമരഹിതമായ ചലനം",
            "ഒരു ദിശയിലുള്ള ചലനം"
        ],
        "answer": "ക്രമരഹിതമായ ചലനം"
    },
    {
        "id": 19,
        "question": "SI സമ്പ്രദായത്തിൽ വൈദ്യുത പ്രവാഹത്തിൻ്റെ യൂണിറ്റ് എന്താണ്?",
        "options": [
            "വോൾട്ട്",
            "ഓം",
            "ആമ്പിയർ",
            "വാട്ട്"
        ],
        "answer": "ആമ്പിയർ"
    },
    {
        "id": 20,
        "question": "ഒരു വസ്തുവിൻ്റെ സ്ഥാനാന്തരത്തിൻ്റെ നിരക്ക് എന്താണ്?",
        "options": [
            "വേഗത",
            "ത്വരണം",
            "പ്രവേഗം",
            "ദൂരം"
        ],
        "answer": "പ്രവേഗം"
    }
]